os_xenapi/__init__.py
os_xenapi/client/XenAPI.py
os_xenapi/client/__init__.py
os_xenapi/client/disk_management.py
os_xenapi/client/exception.py
os_xenapi/client/host_agent.py
os_xenapi/client/host_glance.py
os_xenapi/client/host_management.py
os_xenapi/client/host_network.py
os_xenapi/client/host_xenstore.py
os_xenapi/client/i18n.py
os_xenapi/client/objects.py
os_xenapi/client/session.py
os_xenapi/client/utils.py
os_xenapi/client/vm_management.py
os_xenapi/client/image/__init__.py
os_xenapi/client/image/vdi_handler.py
os_xenapi/client/image/vhd_utils.py
os_xenapi/cmd/__init__.py
os_xenapi/cmd/bootstrap.py
os_xenapi/dom0/README
os_xenapi/dom0/xenapi-plugins.spec
os_xenapi/dom0/etc/xapi.d/plugins/agent.py
os_xenapi/dom0/etc/xapi.d/plugins/bandwidth.py
os_xenapi/dom0/etc/xapi.d/plugins/config_file.py
os_xenapi/dom0/etc/xapi.d/plugins/console.py
os_xenapi/dom0/etc/xapi.d/plugins/dom0_plugin_version.py
os_xenapi/dom0/etc/xapi.d/plugins/dom0_pluginlib.py
os_xenapi/dom0/etc/xapi.d/plugins/glance.py
os_xenapi/dom0/etc/xapi.d/plugins/ipxe.py
os_xenapi/dom0/etc/xapi.d/plugins/kernel.py
os_xenapi/dom0/etc/xapi.d/plugins/migration.py
os_xenapi/dom0/etc/xapi.d/plugins/netwrap.py
os_xenapi/dom0/etc/xapi.d/plugins/partition_utils.py
os_xenapi/dom0/etc/xapi.d/plugins/utils.py
os_xenapi/dom0/etc/xapi.d/plugins/workarounds.py
os_xenapi/dom0/etc/xapi.d/plugins/xenhost.py
os_xenapi/dom0/etc/xapi.d/plugins/xenstore.py
os_xenapi/tests/__init__.py
os_xenapi/tests/base.py
os_xenapi/tests/test_os_xenapi.py
os_xenapi/tests/client/__init__.py
os_xenapi/tests/client/test_host_glance.py
os_xenapi/tests/client/test_objects.py
os_xenapi/tests/client/test_session.py
os_xenapi/tests/client/test_utils.py
os_xenapi/tests/client/image/__init__.py
os_xenapi/tests/client/image/test_init.py
os_xenapi/tests/client/image/test_vdi_handler.py
os_xenapi/tests/client/image/test_vhd_utils.py
os_xenapi/tests/cmd/__init__.py
os_xenapi-0.3.3.dist-info/METADATA
os_xenapi-0.3.3.dist-info/RECORD
os_xenapi-0.3.3.dist-info/WHEEL
os_xenapi-0.3.3.dist-info/entry_points.txt
os_xenapi-0.3.3.dist-info/pbr.json
os_xenapi-0.3.3.dist-info/top_level.txt
