Metadata-Version: 2.1
Name: os-xenapi
Version: 0.3.3
Summary: XenAPI library for OpenStack projects
Home-page: http://www.citrix.com
Author: Citrix
Author-email: openstack@citrix.com
License: UNKNOWN
Platform: UNKNOWN
Classifier: Environment :: OpenStack
Classifier: Intended Audience :: Information Technology
Classifier: Intended Audience :: System Administrators
Classifier: License :: OSI Approved :: Apache Software License
Classifier: Operating System :: POSIX :: Linux
Classifier: Programming Language :: Python
Classifier: Programming Language :: Python :: 2
Classifier: Programming Language :: Python :: 2.7
Classifier: Programming Language :: Python :: 3
Classifier: Programming Language :: Python :: 3.5
Requires-Dist: pbr (!=2.1.0,>=2.0.0)
Requires-Dist: Babel (!=2.4.0,>=2.3.4)
Requires-Dist: eventlet (!=0.18.3,!=0.20.1,<0.21.0,>=0.18.2)
Requires-Dist: oslo.concurrency (>=3.26.0)
Requires-Dist: oslo.log (>=3.36.0)
Requires-Dist: oslo.utils (>=3.33.0)
Requires-Dist: oslo.i18n (>=3.15.3)
Requires-Dist: paramiko (>=2.0.0)
Requires-Dist: six (>=1.10.0)
